mercury/__init__.py
mercury/button.py
mercury/checkbox.py
mercury/columns.py
mercury/download.py
mercury/expander.py
mercury/file.py
mercury/image.py
mercury/indicator.py
mercury/json.py
mercury/manager.py
mercury/md.py
mercury/multiselect.py
mercury/number.py
mercury/pdf.py
mercury/progressbar.py
mercury/select.py
mercury/slider.py
mercury/stop.py
mercury/table.py
mercury/tabs.py
mercury/text.py
mercury/theme.py
mercury/chat/__init__.py
mercury/chat/chat.py
mercury/chat/chatinput.py
mercury/chat/message.py
mercury/tests/__init__.py
mercury/tests/test_multiselect_widget.py
mercury/tests/test_select_widget.py
mercury_app/__init__.py
mercury_app/__main__.py
mercury_app/_version.py
mercury_app/app.py
mercury_app/block_handler.py
mercury_app/custom_contents_handler.py
mercury_app/handlers.py
mercury_app/idle_timeout.py
mercury_app/mercury_hybrid_cm.py
mercury_app/notebooks.py
mercury_app/notebooks_meta.py
mercury_app/root.py
mercury_app/serverextension.py
mercury_app/theme_handler.py
mercury_app/templates/app.html
mercury_app/templates/browser-open.html
mercury_app/templates/error.html
mercury_app/templates/login.html
mercury_app/templates/page.html
mercury_app/templates/root.html
mercury_app/static/.gitkeep
mercury_app/static/1cb1c39ea642f26a4dfe.woff
mercury_app/static/26683bf201fb258a2237.woff
mercury_app/static/30e889b58cbc51adfbb0.woff
mercury_app/static/32792104b5ef69eded90.woff
mercury_app/static/355254db9ca10a09a3b5.woff
mercury_app/static/36e0d72d8a7afc696a3e.woff
mercury_app/static/373c04fd2418f5c77eea.eot
mercury_app/static/3bc6ecaae7ecf6f8d7f8.woff
mercury_app/static/3de784d07b9fa8f104c1.woff
mercury_app/static/3f6d3488cf65374f6f67.woff
mercury_app/static/481e39042508ae313a60.woff
mercury_app/static/5cda41563a095bd70c78.woff
mercury_app/static/721921bab0d001ebff02.woff
mercury_app/static/72bc573386dd1d48c5bb.woff
mercury_app/static/79d088064beb3826054f.eot
mercury_app/static/870673df72e70f87c91a.woff
mercury_app/static/88b98cad3688915e50da.woff
mercury-3.0.0.dist-info/METADATA
mercury-3.0.0.dist-info/WHEEL
mercury-3.0.0.dist-info/entry_points.txt
mercury-3.0.0.dist-info/licenses/LICENSE
mercury-3.0.0.dist-info/RECORD
