Metadata-Version: 2.4
Name: mercury
Version: 3.0.0
Dynamic: Keywords
Summary: Mercury Framework
Project-URL: Homepage, https://github.com/mljar/mercury
Project-URL: Bug Tracker, https://github.com/mljar/mercury/issues
Project-URL: Repository, https://github.com/mljar/mercury.git
Author-email: "MLJAR Sp. z o.o." <contact@mljar.com>
License: 
License-File: LICENSE
Requires-Python: >=3.8
Requires-Dist: anywidget>=0.9.0
Requires-Dist: jupyter-server<3,>=2.0.1
Requires-Dist: jupyterlab-server<3,>=2
Requires-Dist: jupyterlab<5,>=4
Requires-Dist: markdown
Requires-Dist: toml
Provides-Extra: dev
Requires-Dist: isort>=5; extra == 'dev'
Requires-Dist: pytest>=7; extra == 'dev'
